Metadata-Version: 2.1
Name: MqttMonitor
Version: 1.0.5
Summary: Monitor MQTT messages.
Home-page: https://fw-box.com
Author: Hartman Hsieh
Author-email: hartman@fw-box.com
License: GPLv3+
Keywords: MQTT,monitor,serial,view
Platform: UNKNOWN
Classifier: Development Status :: 5 - Production/Stable
Classifier: Operating System :: Microsoft :: Windows
Classifier: License :: OSI Approved :: GNU General Public License v3 or later (GPLv3+)
Classifier: Programming Language :: Python :: 3.5
Classifier: Programming Language :: Python :: 3.6
